{
  "run_id": "haiku_none_task2_rep3",
  "model": "haiku",
  "condition": "none",
  "task": "2",
  "task_complexity": "medium",
  "rep": 3,
  "timestamp": "2026-02-20T00:37:56+00:00",
  "duration_ms": 14816,
  "cli_tool": "claude",
  "raw_output": "{\"type\":\"result\",\"subtype\":\"success\",\"is_error\":false,\"duration_ms\":12296,\"duration_api_ms\":12254,\"num_turns\":2,\"result\":\"I can create the JSON chart specification for you. Here's a comprehensive line chart specification with all the requirements:\\n\\n```json\\n{\\n  \\\"chart_type\\\": \\\"line\\\",\\n  \\\"title\\\": {\\n    \\\"text\\\": \\\"Growth of AI Model Sizes (2017-2024)\\\",\\n    \\\"subtitle\\\": \\\"1000x Expansion in Parameters Over 4 Years\\\"\\n  },\\n  \\\"source\\\": {\\n    \\\"attribution\\\": \\\"Epoch AI, Trends in Machine Learning, 2024\\\"\\n  },\\n  \\\"data\\\": [\\n    { \\\"year\\\": 2017, \\\"model\\\": \\\"Transformer\\\", \\\"parameters\\\": 0.094 },\\n    { \\\"year\\\": 2018, \\\"model\\\": \\\"BERT\\\", \\\"parameters\\\": 0.310 },\\n    { \\\"year\\\": 2019, \\\"model\\\": \\\"GPT-2\\\", \\\"parameters\\\": 1.5 },\\n    { \\\"year\\\": 2020, \\\"model\\\": \\\"GPT-3\\\", \\\"parameters\\\": 17 },\\n    { \\\"year\\\": 2021, \\\"model\\\": \\\"Gopher\\\", \\\"parameters\\\": 175 },\\n    { \\\"year\\\": 2022, \\\"model\\\": \\\"PaLM\\\", \\\"parameters\\\": 540 },\\n    { \\\"year\\\": 2023, \\\"model\\\": \\\"GPT-4\\\", \\\"parameters\\\": 1800 },\\n    { \\\"year\\\": 2024, \\\"model\\\": \\\"Gemini Ultra\\\", \\\"parameters\\\": 12000 }\\n  ],\\n  \\\"axes\\\": {\\n    \\\"x\\\": {\\n      \\\"type\\\": \\\"category\\\",\\n      \\\"label\\\": \\\"Year\\\",\\n      \\\"data_key\\\": \\\"year\\\"\\n    },\\n    \\\"y\\\": {\\n      \\\"type\\\": \\\"log\\\",\\n      \\\"label\\\": \\\"Model Parameters (Billions)\\\",\\n      \\\"data_key\\\": \\\"parameters\\\",\\n      \\\"scale\\\": \\\"logarithmic\\\",\\n      \\\"min\\\": 0.01,\\n      \\\"max\\\": 100000\\n    }\\n  },\\n  \\\"annotations\\\": [\\n    {\\n      \\\"type\\\": \\\"range\\\",\\n      \\\"name\\\": \\\"1000x Growth\\\",\\n      \\\"description\\\": \\\"Expansion from GPT-3 to Gemini Ultra\\\",\\n      \\\"start_year\\\": 2020,\\n      \\\"end_year\\\": 2024,\\n      \\\"start_value\\\": 17,\\n      \\\"end_value\\\": 12000,\\n      \\\"styling\\\": {\\n        \\\"fill_color\\\": \\\"rgba(255, 193, 7, 0.1)\\\",\\n        \\\"border_color\\\": \\\"#FFC107\\\",\\n        \\\"border_width\\\": 2,\\n        \\\"border_style\\\": \\\"dashed\\\"\\n      }\\n    },\\n    {\\n      \\\"type\\\": \\\"point\\\",\\n      \\\"name\\\": \\\"GPT-4 Milestone\\\",\\n      \\\"year\\\": 2023,\\n      \\\"value\\\": 1800,\\n      \\\"label\\\": \\\"GPT-4\\\\n1.8T Parameters\\\",\\n      \\\"styling\\\": {\\n        \\\"marker_color\\\": \\\"#FF5722\\\",\\n        \\\"marker_size\\\": 10,\\n        \\\"label_position\\\": \\\"top\\\",\\n        \\\"label_background\\\": \\\"rgba(255, 87, 34, 0.2)\\\"\\n      }\\n    }\\n  ],\\n  \\\"line_config\\\": {\\n    \\\"color\\\": \\\"#2196F3\\\",\\n    \\\"width\\\": 3,\\n    \\\"curve\\\": \\\"monotone\\\"\\n  },\\n  \\\"grid\\\": {\\n    \\\"show_x\\\": true,\\n    \\\"show_y\\\": true,\\n    \\\"x_interval\\\": 1,\\n    \\\"y_logarithmic\\\": true\\n  },\\n  \\\"legend\\\": {\\n    \\\"show\\\": true,\\n    \\\"position\\\": \\\"top-right\\\",\\n    \\\"items\\\": [\\n      {\\n        \\\"name\\\": \\\"Largest Model Size\\\",\\n        \\\"color\\\": \\\"#2196F3\\\"\\n      }\\n    ]\\n  }\\n}\\n```\\n\\n**Key features of this specification:**\\n\\n1. **Chart Type**: Line chart with monotone curve smoothing\\n2. **Title**: Clear main title with subtitle highlighting the 1000x growth metric\\n3. **Data**: All 8 data points with year, model name, and parameters\\n4. **Axes**:\\n   - **X-axis**: Years (2017-2024) as categories\\n   - **Y-axis**: Logarithmic scale (essential for showing 0.094 to 12000 on same chart)\\n5. **Annotations**:\\n   - **Range highlight**: Golden shaded region showing 1000x growth from GPT-3 (2020) to Gemini Ultra (2024)\\n   - **Point marker**: Red dot at GPT-4 (2023, 1.8T) with label\\n6. **Source attribution**: Epoch AI credit at the bottom\\n7. **Visual styling**: Professional blue line with grid lines and legend\\n\\nThe logarithmic scale on the Y-axis is crucial hereâ€”it makes the exponential growth visible while accommodating the massive range from 94M to 12T parameters.\",\"stop_reason\":null,\"session_id\":\"23725beb-e894-4b5e-8566-29cbb70c6a51\",\"total_cost_usd\":0.018853100000000005,\"usage\":{\"input_tokens\":10,\"cache_creation_input_tokens\":1054,\"cache_read_input_tokens\":67306,\"output_tokens\":2159,\"server_tool_use\":{\"web_search_requests\":0,\"web_fetch_requests\":0},\"service_tier\":\"standard\",\"cache_creation\":{\"ephemeral_1h_input_tokens\":1054,\"ephemeral_5m_input_tokens\":0},\"inference_geo\":\"\",\"iterations\":[],\"speed\":\"standard\"},\"modelUsage\":{\"claude-haiku-4-5-20251001\":{\"inputTokens\":10,\"outputTokens\":2159,\"cacheReadInputTokens\":67306,\"cacheCreationInputTokens\":1054,\"webSearchRequests\":0,\"costUSD\":0.018853100000000005,\"contextWindow\":200000,\"maxOutputTokens\":32000}},\"permission_denials\":[{\"tool_name\":\"Write\",\"tool_use_id\":\"toolu_01VzhMexujaCFEHubgBwKthS\",\"tool_input\":{\"file_path\":\"/tmp/ai-model-growth-chart.json\",\"content\":\"{\\n  \\\"chart_type\\\": \\\"line\\\",\\n  \\\"title\\\": {\\n    \\\"text\\\": \\\"Growth of AI Model Sizes (2017-2024)\\\",\\n    \\\"subtitle\\\": \\\"1000x Expansion in Parameters Over 4 Years\\\"\\n  },\\n  \\\"source\\\": {\\n    \\\"attribution\\\": \\\"Epoch AI, Trends in Machine Learning, 2024\\\"\\n  },\\n  \\\"data\\\": [\\n    {\\n      \\\"year\\\": 2017,\\n      \\\"model\\\": \\\"Transformer\\\",\\n      \\\"parameters\\\": 0.094\\n    },\\n    {\\n      \\\"year\\\": 2018,\\n      \\\"model\\\": \\\"BERT\\\",\\n      \\\"parameters\\\": 0.310\\n    },\\n    {\\n      \\\"year\\\": 2019,\\n      \\\"model\\\": \\\"GPT-2\\\",\\n      \\\"parameters\\\": 1.5\\n    },\\n    {\\n      \\\"year\\\": 2020,\\n      \\\"model\\\": \\\"GPT-3\\\",\\n      \\\"parameters\\\": 17\\n    },\\n    {\\n      \\\"year\\\": 2021,\\n      \\\"model\\\": \\\"Gopher\\\",\\n      \\\"parameters\\\": 175\\n    },\\n    {\\n      \\\"year\\\": 2022,\\n      \\\"model\\\": \\\"PaLM\\\",\\n      \\\"parameters\\\": 540\\n    },\\n    {\\n      \\\"year\\\": 2023,\\n      \\\"model\\\": \\\"GPT-4\\\",\\n      \\\"parameters\\\": 1800\\n    },\\n    {\\n      \\\"year\\\": 2024,\\n      \\\"model\\\": \\\"Gemini Ultra\\\",\\n      \\\"parameters\\\": 12000\\n    }\\n  ],\\n  \\\"axes\\\": {\\n    \\\"x\\\": {\\n      \\\"type\\\": \\\"category\\\",\\n      \\\"label\\\": \\\"Year\\\",\\n      \\\"data_key\\\": \\\"year\\\"\\n    },\\n    \\\"y\\\": {\\n      \\\"type\\\": \\\"log\\\",\\n      \\\"label\\\": \\\"Model Parameters (Billions)\\\",\\n      \\\"data_key\\\": \\\"parameters\\\",\\n      \\\"scale\\\": \\\"logarithmic\\\",\\n      \\\"min\\\": 0.01,\\n      \\\"max\\\": 100000\\n    }\\n  },\\n  \\\"annotations\\\": [\\n    {\\n      \\\"type\\\": \\\"range\\\",\\n      \\\"name\\\": \\\"1000x Growth\\\",\\n      \\\"description\\\": \\\"Expansion from GPT-3 to Gemini Ultra\\\",\\n      \\\"start_year\\\": 2020,\\n      \\\"end_year\\\": 2024,\\n      \\\"start_value\\\": 17,\\n      \\\"end_value\\\": 12000,\\n      \\\"styling\\\": {\\n        \\\"fill_color\\\": \\\"rgba(255, 193, 7, 0.1)\\\",\\n        \\\"border_color\\\": \\\"#FFC107\\\",\\n        \\\"border_width\\\": 2,\\n        \\\"border_style\\\": \\\"dashed\\\"\\n      }\\n    },\\n    {\\n      \\\"type\\\": \\\"point\\\",\\n      \\\"name\\\": \\\"GPT-4 Milestone\\\",\\n      \\\"year\\\": 2023,\\n      \\\"value\\\": 1800,\\n      \\\"label\\\": \\\"GPT-4\\\\n1.8T Parameters\\\",\\n      \\\"styling\\\": {\\n        \\\"marker_color\\\": \\\"#FF5722\\\",\\n        \\\"marker_size\\\": 10,\\n        \\\"label_position\\\": \\\"top\\\",\\n        \\\"label_background\\\": \\\"rgba(255, 87, 34, 0.2)\\\"\\n      }\\n    }\\n  ],\\n  \\\"line_config\\\": {\\n    \\\"color\\\": \\\"#2196F3\\\",\\n    \\\"width\\\": 3,\\n    \\\"curve\\\": \\\"monotone\\\"\\n  },\\n  \\\"grid\\\": {\\n    \\\"show_x\\\": true,\\n    \\\"show_y\\\": true,\\n    \\\"x_interval\\\": 1,\\n    \\\"y_logarithmic\\\": true\\n  },\\n  \\\"legend\\\": {\\n    \\\"show\\\": true,\\n    \\\"position\\\": \\\"top-right\\\",\\n    \\\"items\\\": [\\n      {\\n        \\\"name\\\": \\\"Largest Model Size\\\",\\n        \\\"color\\\": \\\"#2196F3\\\"\\n      }\\n    ]\\n  }\\n}\\n\"}}],\"uuid\":\"31535e07-6def-4d77-8587-82c78888ab44\"}"
}
