{
  "run_id": "haiku_none_task1_rep3",
  "model": "haiku",
  "condition": "none",
  "task": "1",
  "task_complexity": "simple",
  "rep": 3,
  "timestamp": "2026-02-20T00:37:06+00:00",
  "duration_ms": 25179,
  "cli_tool": "claude",
  "raw_output": "{\"type\":\"result\",\"subtype\":\"success\",\"is_error\":false,\"duration_ms\":12887,\"duration_api_ms\":12842,\"num_turns\":2,\"result\":\"I'll create the JSON chart specification. Here's the complete structure:\\n\\n```json\\n{\\n  \\\"chart_type\\\": \\\"bar\\\",\\n  \\\"title\\\": {\\n    \\\"text\\\": \\\"2023 GDP Comparison by Economy\\\",\\n    \\\"subtitle\\\": \\\"Selected major economies (USD billions)\\\"\\n  },\\n  \\\"source\\\": \\\"IMF World Economic Outlook, 2024\\\",\\n  \\\"data\\\": [\\n    {\\n      \\\"country\\\": \\\"USA\\\",\\n      \\\"gdp\\\": 25462,\\n      \\\"highlight\\\": true\\n    },\\n    {\\n      \\\"country\\\": \\\"China\\\",\\n      \\\"gdp\\\": 17963,\\n      \\\"highlight\\\": true\\n    },\\n    {\\n      \\\"country\\\": \\\"Japan\\\",\\n      \\\"gdp\\\": 4231\\n    },\\n    {\\n      \\\"country\\\": \\\"Germany\\\",\\n      \\\"gdp\\\": 4072\\n    },\\n    {\\n      \\\"country\\\": \\\"India\\\",\\n      \\\"gdp\\\": 3385\\n    }\\n  ],\\n  \\\"axes\\\": {\\n    \\\"x\\\": {\\n      \\\"type\\\": \\\"category\\\",\\n      \\\"label\\\": \\\"Economy\\\",\\n      \\\"field\\\": \\\"country\\\"\\n    },\\n    \\\"y\\\": {\\n      \\\"type\\\": \\\"linear\\\",\\n      \\\"label\\\": \\\"GDP (USD Billions)\\\",\\n      \\\"field\\\": \\\"gdp\\\",\\n      \\\"min\\\": 0,\\n      \\\"max\\\": 28000\\n    }\\n  },\\n  \\\"styling\\\": {\\n    \\\"colors\\\": {\\n      \\\"default\\\": \\\"#4472C4\\\",\\n      \\\"highlight\\\": \\\"#FF6B6B\\\"\\n    },\\n    \\\"barOpacity\\\": 0.8\\n  },\\n  \\\"annotations\\\": [\\n    {\\n      \\\"type\\\": \\\"gap-highlight\\\",\\n      \\\"label\\\": \\\"USA-China Gap\\\",\\n      \\\"value\\\": 7499,\\n      \\\"description\\\": \\\"$7,499 billion difference\\\",\\n      \\\"position\\\": \\\"between\\\",\\n      \\\"countries\\\": [\\\"USA\\\", \\\"China\\\"],\\n      \\\"style\\\": {\\n        \\\"color\\\": \\\"#FF6B6B\\\",\\n        \\\"opacity\\\": 0.3,\\n        \\\"lineStyle\\\": \\\"dashed\\\"\\n      }\\n    },\\n    {\\n      \\\"type\\\": \\\"value-label\\\",\\n      \\\"country\\\": \\\"USA\\\",\\n      \\\"text\\\": \\\"$25.5T\\\",\\n      \\\"position\\\": \\\"top\\\"\\n    },\\n    {\\n      \\\"type\\\": \\\"value-label\\\",\\n      \\\"country\\\": \\\"China\\\",\\n      \\\"text\\\": \\\"$18.0T\\\",\\n      \\\"position\\\": \\\"top\\\"\\n    }\\n  ],\\n  \\\"sorting\\\": {\\n    \\\"field\\\": \\\"gdp\\\",\\n    \\\"order\\\": \\\"descending\\\"\\n  },\\n  \\\"metadata\\\": {\\n    \\\"year\\\": 2023,\\n    \\\"currency\\\": \\\"USD\\\",\\n    \\\"unit\\\": \\\"billions\\\"\\n  }\\n}\\n```\\n\\n**Key features:**\\n\\n- **chart_type**: Bar chart format\\n- **title**: Main title with subtitle providing context\\n- **source**: IMF attribution for data credibility\\n- **data**: Sorted descending by GDP, with USA and China flagged as highlighted\\n- **axes**: Category axis for countries, linear axis for GDP values (0-28,000 billion range)\\n- **annotations**:\\n  - Gap highlight between USA and China ($7.5T difference) with visual styling\\n  - Value labels on top of USA and China bars for emphasis\\n- **styling**: Highlight color (red) for featured economies, blue for others\\n- **metadata**: Year, currency, and unit information for reference\\n\\nThis specification can be rendered using charting libraries like D3.js, Chart.js, or Vega-Lite.\",\"stop_reason\":null,\"session_id\":\"ca5f1f3a-bac0-4951-9ae0-4e7b1c2f96b3\",\"total_cost_usd\":0.0154134,\"usage\":{\"input_tokens\":10,\"cache_creation_input_tokens\":764,\"cache_read_input_tokens\":67084,\"output_tokens\":1548,\"server_tool_use\":{\"web_search_requests\":0,\"web_fetch_requests\":0},\"service_tier\":\"standard\",\"cache_creation\":{\"ephemeral_1h_input_tokens\":764,\"ephemeral_5m_input_tokens\":0},\"inference_geo\":\"\",\"iterations\":[],\"speed\":\"standard\"},\"modelUsage\":{\"claude-haiku-4-5-20251001\":{\"inputTokens\":10,\"outputTokens\":1548,\"cacheReadInputTokens\":67084,\"cacheCreationInputTokens\":764,\"webSearchRequests\":0,\"costUSD\":0.0154134,\"contextWindow\":200000,\"maxOutputTokens\":32000}},\"permission_denials\":[{\"tool_name\":\"Write\",\"tool_use_id\":\"toolu_01ReiXZbiPfkDPQeXu8RUvnx\",\"tool_input\":{\"file_path\":\"/tmp/gdp_chart.json\",\"content\":\"{\\n  \\\"chart_type\\\": \\\"bar\\\",\\n  \\\"title\\\": {\\n    \\\"text\\\": \\\"2023 GDP Comparison by Economy\\\",\\n    \\\"subtitle\\\": \\\"Selected major economies (USD billions)\\\"\\n  },\\n  \\\"source\\\": \\\"IMF World Economic Outlook, 2024\\\",\\n  \\\"data\\\": [\\n    {\\n      \\\"country\\\": \\\"USA\\\",\\n      \\\"gdp\\\": 25462,\\n      \\\"highlight\\\": true\\n    },\\n    {\\n      \\\"country\\\": \\\"China\\\",\\n      \\\"gdp\\\": 17963,\\n      \\\"highlight\\\": true\\n    },\\n    {\\n      \\\"country\\\": \\\"Japan\\\",\\n      \\\"gdp\\\": 4231\\n    },\\n    {\\n      \\\"country\\\": \\\"Germany\\\",\\n      \\\"gdp\\\": 4072\\n    },\\n    {\\n      \\\"country\\\": \\\"India\\\",\\n      \\\"gdp\\\": 3385\\n    }\\n  ],\\n  \\\"axes\\\": {\\n    \\\"x\\\": {\\n      \\\"type\\\": \\\"category\\\",\\n      \\\"label\\\": \\\"Economy\\\",\\n      \\\"field\\\": \\\"country\\\"\\n    },\\n    \\\"y\\\": {\\n      \\\"type\\\": \\\"linear\\\",\\n      \\\"label\\\": \\\"GDP (USD Billions)\\\",\\n      \\\"field\\\": \\\"gdp\\\",\\n      \\\"min\\\": 0,\\n      \\\"max\\\": 28000\\n    }\\n  },\\n  \\\"styling\\\": {\\n    \\\"colors\\\": {\\n      \\\"default\\\": \\\"#4472C4\\\",\\n      \\\"highlight\\\": \\\"#FF6B6B\\\"\\n    },\\n    \\\"barOpacity\\\": 0.8\\n  },\\n  \\\"annotations\\\": [\\n    {\\n      \\\"type\\\": \\\"gap-highlight\\\",\\n      \\\"label\\\": \\\"USA-China Gap\\\",\\n      \\\"value\\\": 7499,\\n      \\\"description\\\": \\\"$7,499 billion difference\\\",\\n      \\\"position\\\": \\\"between\\\",\\n      \\\"countries\\\": [\\\"USA\\\", \\\"China\\\"],\\n      \\\"style\\\": {\\n        \\\"color\\\": \\\"#FF6B6B\\\",\\n        \\\"opacity\\\": 0.3,\\n        \\\"lineStyle\\\": \\\"dashed\\\"\\n      }\\n    },\\n    {\\n      \\\"type\\\": \\\"value-label\\\",\\n      \\\"country\\\": \\\"USA\\\",\\n      \\\"text\\\": \\\"$25.5T\\\",\\n      \\\"position\\\": \\\"top\\\"\\n    },\\n    {\\n      \\\"type\\\": \\\"value-label\\\",\\n      \\\"country\\\": \\\"China\\\",\\n      \\\"text\\\": \\\"$18.0T\\\",\\n      \\\"position\\\": \\\"top\\\"\\n    }\\n  ],\\n  \\\"sorting\\\": {\\n    \\\"field\\\": \\\"gdp\\\",\\n    \\\"order\\\": \\\"descending\\\"\\n  },\\n  \\\"metadata\\\": {\\n    \\\"year\\\": 2023,\\n    \\\"currency\\\": \\\"USD\\\",\\n    \\\"unit\\\": \\\"billions\\\"\\n  }\\n}\\n\"}}],\"uuid\":\"61ecddaf-63e0-4604-80bb-fba7100ef49d\"}"
}
