{
  "run_id": "opus_markdown_task3_rep1",
  "model": "opus",
  "condition": "markdown",
  "task": "3",
  "task_complexity": "complex",
  "rep": 1,
  "timestamp": "2026-02-20T06:33:27+00:00",
  "duration_ms": 109639,
  "cli_tool": "claude",
  "raw_output": "{\"type\":\"result\",\"subtype\":\"success\",\"is_error\":false,\"duration_ms\":65591,\"duration_api_ms\":65542,\"num_turns\":2,\"result\":\"Here's the chart specification:\\n\\n```json\\n{\\n  \\\"chart\\\": {\\n    \\\"type\\\": \\\"line\\\",\\n    \\\"title\\\": \\\"Azure overtook AWS as the largest cloud provider in mid-2024\\\",\\n    \\\"subtitle\\\": \\\"Quarterly cloud revenue, USD billions\\\",\\n    \\\"source\\\": \\\"Source: Company earnings reports, 2023–2024\\\",\\n    \\\"aspectRatio\\\": \\\"16:9\\\",\\n    \\\"width\\\": 800,\\n    \\\"height\\\": 450,\\n    \\\"background\\\": \\\"#F5F5F5\\\",\\n    \\\"margins\\\": { \\\"top\\\": 80, \\\"right\\\": 120, \\\"bottom\\\": 60, \\\"left\\\": 60 }\\n  },\\n  \\\"axes\\\": {\\n    \\\"x\\\": {\\n      \\\"field\\\": \\\"quarter\\\",\\n      \\\"tickRotation\\\": 0,\\n      \\\"gridlines\\\": false,\\n      \\\"spine\\\": true,\\n      \\\"spineColor\\\": \\\"#333333\\\"\\n    },\\n    \\\"y\\\": {\\n      \\\"field\\\": \\\"revenue\\\",\\n      \\\"domain\\\": [0, 35],\\n      \\\"tickValues\\\": [0, 5, 10, 15, 20, 25, 30, 35],\\n      \\\"tickFormat\\\": \\\"${}B\\\",\\n      \\\"gridlines\\\": {\\n        \\\"show\\\": true,\\n        \\\"color\\\": \\\"#D0D0D0\\\",\\n        \\\"strokeDasharray\\\": \\\"3,3\\\",\\n        \\\"strokeWidth\\\": 0.5\\n      },\\n      \\\"spine\\\": false\\n    },\\n    \\\"removeSpines\\\": [\\\"top\\\", \\\"right\\\"]\\n  },\\n  \\\"data\\\": [\\n    { \\\"quarter\\\": \\\"Q1 '23\\\", \\\"AWS\\\": 21.3, \\\"Azure\\\": 21.0, \\\"GCP\\\": 7.0 },\\n    { \\\"quarter\\\": \\\"Q2 '23\\\", \\\"AWS\\\": 22.1, \\\"Azure\\\": 23.0, \\\"GCP\\\": 8.0 },\\n    { \\\"quarter\\\": \\\"Q3 '23\\\", \\\"AWS\\\": 23.1, \\\"Azure\\\": 24.0, \\\"GCP\\\": 8.4 },\\n    { \\\"quarter\\\": \\\"Q4 '23\\\", \\\"AWS\\\": 24.2, \\\"Azure\\\": 25.0, \\\"GCP\\\": 9.2 },\\n    { \\\"quarter\\\": \\\"Q1 '24\\\", \\\"AWS\\\": 25.0, \\\"Azure\\\": 26.0, \\\"GCP\\\": 9.6 },\\n    { \\\"quarter\\\": \\\"Q2 '24\\\", \\\"AWS\\\": 26.0, \\\"Azure\\\": 28.0, \\\"GCP\\\": 10.3 },\\n    { \\\"quarter\\\": \\\"Q3 '24\\\", \\\"AWS\\\": 27.5, \\\"Azure\\\": 29.0, \\\"GCP\\\": 11.4 },\\n    { \\\"quarter\\\": \\\"Q4 '24\\\", \\\"AWS\\\": 28.8, \\\"Azure\\\": 30.0, \\\"GCP\\\": 12.0 }\\n  ],\\n  \\\"series\\\": [\\n    {\\n      \\\"name\\\": \\\"Azure\\\",\\n      \\\"field\\\": \\\"Azure\\\",\\n      \\\"color\\\": \\\"#C74634\\\",\\n      \\\"strokeWidth\\\": 3,\\n      \\\"directLabel\\\": {\\n        \\\"text\\\": \\\"Azure\\\",\\n        \\\"position\\\": \\\"end\\\",\\n        \\\"offsetX\\\": 8,\\n        \\\"fontWeight\\\": \\\"bold\\\",\\n        \\\"fontSize\\\": 13,\\n        \\\"color\\\": \\\"#C74634\\\"\\n      }\\n    },\\n    {\\n      \\\"name\\\": \\\"AWS\\\",\\n      \\\"field\\\": \\\"AWS\\\",\\n      \\\"color\\\": \\\"#1A476F\\\",\\n      \\\"strokeWidth\\\": 3,\\n      \\\"directLabel\\\": {\\n        \\\"text\\\": \\\"AWS\\\",\\n        \\\"position\\\": \\\"end\\\",\\n        \\\"offsetX\\\": 8,\\n        \\\"fontWeight\\\": \\\"bold\\\",\\n        \\\"fontSize\\\": 13,\\n        \\\"color\\\": \\\"#1A476F\\\"\\n      }\\n    },\\n    {\\n      \\\"name\\\": \\\"GCP\\\",\\n      \\\"field\\\": \\\"GCP\\\",\\n      \\\"color\\\": \\\"#5D666F\\\",\\n      \\\"strokeWidth\\\": 2,\\n      \\\"directLabel\\\": {\\n        \\\"text\\\": \\\"GCP\\\",\\n        \\\"position\\\": \\\"end\\\",\\n        \\\"offsetX\\\": 8,\\n        \\\"fontWeight\\\": \\\"normal\\\",\\n        \\\"fontSize\\\": 13,\\n        \\\"color\\\": \\\"#5D666F\\\"\\n      }\\n    }\\n  ],\\n  \\\"annotations\\\": [\\n    {\\n      \\\"type\\\": \\\"point\\\",\\n      \\\"dataIndex\\\": 5,\\n      \\\"series\\\": \\\"Azure\\\",\\n      \\\"marker\\\": {\\n        \\\"shape\\\": \\\"circle\\\",\\n        \\\"radius\\\": 6,\\n        \\\"fill\\\": \\\"#C74634\\\",\\n        \\\"stroke\\\": \\\"#FFFFFF\\\",\\n        \\\"strokeWidth\\\": 2\\n      }\\n    },\\n    {\\n      \\\"type\\\": \\\"point\\\",\\n      \\\"dataIndex\\\": 5,\\n      \\\"series\\\": \\\"AWS\\\",\\n      \\\"marker\\\": {\\n        \\\"shape\\\": \\\"circle\\\",\\n        \\\"radius\\\": 6,\\n        \\\"fill\\\": \\\"#1A476F\\\",\\n        \\\"stroke\\\": \\\"#FFFFFF\\\",\\n        \\\"strokeWidth\\\": 2\\n      }\\n    },\\n    {\\n      \\\"type\\\": \\\"text\\\",\\n      \\\"text\\\": \\\"Azure pulls ahead\\\\nin Q2 2024\\\",\\n      \\\"anchor\\\": { \\\"dataIndex\\\": 5, \\\"series\\\": \\\"Azure\\\" },\\n      \\\"offsetX\\\": -80,\\n      \\\"offsetY\\\": -35,\\n      \\\"fontSize\\\": 12,\\n      \\\"fontStyle\\\": \\\"italic\\\",\\n      \\\"color\\\": \\\"#333333\\\",\\n      \\\"leaderLine\\\": {\\n        \\\"show\\\": true,\\n        \\\"stroke\\\": \\\"#999999\\\",\\n        \\\"strokeWidth\\\": 1\\n      }\\n    },\\n    {\\n      \\\"type\\\": \\\"verticalRule\\\",\\n      \\\"dataIndex\\\": 5,\\n      \\\"stroke\\\": \\\"#999999\\\",\\n      \\\"strokeDasharray\\\": \\\"4,3\\\",\\n      \\\"strokeWidth\\\": 1,\\n      \\\"opacity\\\": 0.5\\n    }\\n  ],\\n  \\\"typography\\\": {\\n    \\\"fontFamily\\\": \\\"Inter, Helvetica, Arial, sans-serif\\\",\\n    \\\"title\\\": { \\\"fontSize\\\": 18, \\\"fontWeight\\\": \\\"bold\\\", \\\"color\\\": \\\"#1A1A1A\\\" },\\n    \\\"subtitle\\\": { \\\"fontSize\\\": 13, \\\"fontWeight\\\": \\\"normal\\\", \\\"color\\\": \\\"#5D666F\\\" },\\n    \\\"source\\\": { \\\"fontSize\\\": 11, \\\"color\\\": \\\"#999999\\\", \\\"position\\\": \\\"bottom-left\\\" },\\n    \\\"axisLabels\\\": { \\\"fontSize\\\": 12, \\\"color\\\": \\\"#5D666F\\\" }\\n  },\\n  \\\"style\\\": {\\n    \\\"lineInterpolation\\\": \\\"linear\\\",\\n    \\\"no3D\\\": true,\\n    \\\"noShadows\\\": true,\\n    \\\"noDecorations\\\": true\\n  }\\n}\\n```\\n\\nKey design decisions following the style guidelines:\\n\\n- **Title as insight**: \\\"Azure overtook AWS as the largest cloud provider in mid-2024\\\" — states the finding, not just \\\"Cloud Revenue by Provider\\\"\\n- **Accent color for the story**: Azure gets the red accent (`#C74634`) since it's the key narrative; AWS uses primary blue (`#1A476F`); GCP is muted gray (`#5D666F`)\\n- **Direct labels** instead of a legend — only 3 series, so labels sit at the end of each line\\n- **Crossover annotation**: A dashed vertical rule at Q2 '24 with emphasized dots on both Azure and AWS, plus an italic callout (\\\"Azure pulls ahead in Q2 2024\\\") with a leader line\\n- **Y-axis starts at zero** and uses subtle dashed gridlines\\n- **Top and right spines removed** for a clean Economist look\\n- **16:9 aspect ratio** appropriate for time series\\n- **No chartjunk**: no 3D, no shadows, no decorations\",\"stop_reason\":null,\"session_id\":\"df65d7a3-051e-4b83-a9ff-d55e972afa85\",\"total_cost_usd\":0.3120485,\"usage\":{\"input_tokens\":4,\"cache_creation_input_tokens\":33160,\"cache_read_input_tokens\":31357,\"output_tokens\":3564,\"server_tool_use\":{\"web_search_requests\":0,\"web_fetch_requests\":0},\"service_tier\":\"standard\",\"cache_creation\":{\"ephemeral_1h_input_tokens\":33160,\"ephemeral_5m_input_tokens\":0},\"inference_geo\":\"\",\"iterations\":[],\"speed\":\"standard\"},\"modelUsage\":{\"claude-opus-4-6\":{\"inputTokens\":4,\"outputTokens\":3564,\"cacheReadInputTokens\":31357,\"cacheCreationInputTokens\":33160,\"webSearchRequests\":0,\"costUSD\":0.3120485,\"contextWindow\":200000,\"maxOutputTokens\":32000}},\"permission_denials\":[{\"tool_name\":\"Write\",\"tool_use_id\":\"toolu_01YKoEvv2DZStnaparqW1woy\",\"tool_input\":{\"file_path\":\"/tmp/cloud_revenue_chart.json\",\"content\":\"{\\n  \\\"chart\\\": {\\n    \\\"type\\\": \\\"line\\\",\\n    \\\"title\\\": \\\"Azure overtook AWS as the largest cloud provider in mid-2024\\\",\\n    \\\"subtitle\\\": \\\"Quarterly cloud revenue, USD billions\\\",\\n    \\\"source\\\": \\\"Source: Company earnings reports, 2023–2024\\\",\\n    \\\"aspectRatio\\\": \\\"16:9\\\",\\n    \\\"width\\\": 800,\\n    \\\"height\\\": 450,\\n    \\\"background\\\": \\\"#F5F5F5\\\",\\n    \\\"margins\\\": {\\n      \\\"top\\\": 80,\\n      \\\"right\\\": 120,\\n      \\\"bottom\\\": 60,\\n      \\\"left\\\": 60\\n    }\\n  },\\n  \\\"axes\\\": {\\n    \\\"x\\\": {\\n      \\\"field\\\": \\\"quarter\\\",\\n      \\\"label\\\": null,\\n      \\\"tickRotation\\\": 0,\\n      \\\"gridlines\\\": false,\\n      \\\"spine\\\": true,\\n      \\\"spineColor\\\": \\\"#333333\\\"\\n    },\\n    \\\"y\\\": {\\n      \\\"field\\\": \\\"revenue\\\",\\n      \\\"label\\\": null,\\n      \\\"domain\\\": [0, 35],\\n      \\\"tickValues\\\": [0, 5, 10, 15, 20, 25, 30, 35],\\n      \\\"tickFormat\\\": \\\"${}B\\\",\\n      \\\"gridlines\\\": {\\n        \\\"show\\\": true,\\n        \\\"color\\\": \\\"#D0D0D0\\\",\\n        \\\"strokeDasharray\\\": \\\"3,3\\\",\\n        \\\"strokeWidth\\\": 0.5\\n      },\\n      \\\"spine\\\": false\\n    },\\n    \\\"removeSpines\\\": [\\\"top\\\", \\\"right\\\"]\\n  },\\n  \\\"data\\\": [\\n    { \\\"quarter\\\": \\\"Q1 '23\\\", \\\"AWS\\\": 21.3, \\\"Azure\\\": 21.0, \\\"GCP\\\": 7.0 },\\n    { \\\"quarter\\\": \\\"Q2 '23\\\", \\\"AWS\\\": 22.1, \\\"Azure\\\": 23.0, \\\"GCP\\\": 8.0 },\\n    { \\\"quarter\\\": \\\"Q3 '23\\\", \\\"AWS\\\": 23.1, \\\"Azure\\\": 24.0, \\\"GCP\\\": 8.4 },\\n    { \\\"quarter\\\": \\\"Q4 '23\\\", \\\"AWS\\\": 24.2, \\\"Azure\\\": 25.0, \\\"GCP\\\": 9.2 },\\n    { \\\"quarter\\\": \\\"Q1 '24\\\", \\\"AWS\\\": 25.0, \\\"Azure\\\": 26.0, \\\"GCP\\\": 9.6 },\\n    { \\\"quarter\\\": \\\"Q2 '24\\\", \\\"AWS\\\": 26.0, \\\"Azure\\\": 28.0, \\\"GCP\\\": 10.3 },\\n    { \\\"quarter\\\": \\\"Q3 '24\\\", \\\"AWS\\\": 27.5, \\\"Azure\\\": 29.0, \\\"GCP\\\": 11.4 },\\n    { \\\"quarter\\\": \\\"Q4 '24\\\", \\\"AWS\\\": 28.8, \\\"Azure\\\": 30.0, \\\"GCP\\\": 12.0 }\\n  ],\\n  \\\"series\\\": [\\n    {\\n      \\\"name\\\": \\\"Azure\\\",\\n      \\\"field\\\": \\\"Azure\\\",\\n      \\\"color\\\": \\\"#C74634\\\",\\n      \\\"strokeWidth\\\": 3,\\n      \\\"directLabel\\\": {\\n        \\\"text\\\": \\\"Azure\\\",\\n        \\\"position\\\": \\\"end\\\",\\n        \\\"offsetX\\\": 8,\\n        \\\"offsetY\\\": 0,\\n        \\\"fontWeight\\\": \\\"bold\\\",\\n        \\\"fontSize\\\": 13,\\n        \\\"color\\\": \\\"#C74634\\\"\\n      }\\n    },\\n    {\\n      \\\"name\\\": \\\"AWS\\\",\\n      \\\"field\\\": \\\"AWS\\\",\\n      \\\"color\\\": \\\"#1A476F\\\",\\n      \\\"strokeWidth\\\": 3,\\n      \\\"directLabel\\\": {\\n        \\\"text\\\": \\\"AWS\\\",\\n        \\\"position\\\": \\\"end\\\",\\n        \\\"offsetX\\\": 8,\\n        \\\"offsetY\\\": 0,\\n        \\\"fontWeight\\\": \\\"bold\\\",\\n        \\\"fontSize\\\": 13,\\n        \\\"color\\\": \\\"#1A476F\\\"\\n      }\\n    },\\n    {\\n      \\\"name\\\": \\\"GCP\\\",\\n      \\\"field\\\": \\\"GCP\\\",\\n      \\\"color\\\": \\\"#5D666F\\\",\\n      \\\"strokeWidth\\\": 2,\\n      \\\"directLabel\\\": {\\n        \\\"text\\\": \\\"GCP\\\",\\n        \\\"position\\\": \\\"end\\\",\\n        \\\"offsetX\\\": 8,\\n        \\\"offsetY\\\": 0,\\n        \\\"fontWeight\\\": \\\"normal\\\",\\n        \\\"fontSize\\\": 13,\\n        \\\"color\\\": \\\"#5D666F\\\"\\n      }\\n    }\\n  ],\\n  \\\"annotations\\\": [\\n    {\\n      \\\"type\\\": \\\"point\\\",\\n      \\\"dataIndex\\\": 5,\\n      \\\"series\\\": \\\"Azure\\\",\\n      \\\"marker\\\": {\\n        \\\"shape\\\": \\\"circle\\\",\\n        \\\"radius\\\": 6,\\n        \\\"fill\\\": \\\"#C74634\\\",\\n        \\\"stroke\\\": \\\"#FFFFFF\\\",\\n        \\\"strokeWidth\\\": 2\\n      }\\n    },\\n    {\\n      \\\"type\\\": \\\"point\\\",\\n      \\\"dataIndex\\\": 5,\\n      \\\"series\\\": \\\"AWS\\\",\\n      \\\"marker\\\": {\\n        \\\"shape\\\": \\\"circle\\\",\\n        \\\"radius\\\": 6,\\n        \\\"fill\\\": \\\"#1A476F\\\",\\n        \\\"stroke\\\": \\\"#FFFFFF\\\",\\n        \\\"strokeWidth\\\": 2\\n      }\\n    },\\n    {\\n      \\\"type\\\": \\\"text\\\",\\n      \\\"text\\\": \\\"Azure pulls ahead\\\\nin Q2 2024\\\",\\n      \\\"anchor\\\": {\\n        \\\"dataIndex\\\": 5,\\n        \\\"series\\\": \\\"Azure\\\"\\n      },\\n      \\\"offsetX\\\": -80,\\n      \\\"offsetY\\\": -35,\\n      \\\"fontSize\\\": 12,\\n      \\\"fontStyle\\\": \\\"italic\\\",\\n      \\\"color\\\": \\\"#333333\\\",\\n      \\\"leaderLine\\\": {\\n        \\\"show\\\": true,\\n        \\\"stroke\\\": \\\"#999999\\\",\\n        \\\"strokeWidth\\\": 1\\n      }\\n    },\\n    {\\n      \\\"type\\\": \\\"verticalRule\\\",\\n      \\\"dataIndex\\\": 5,\\n      \\\"stroke\\\": \\\"#999999\\\",\\n      \\\"strokeDasharray\\\": \\\"4,3\\\",\\n      \\\"strokeWidth\\\": 1,\\n      \\\"opacity\\\": 0.5\\n    }\\n  ],\\n  \\\"typography\\\": {\\n    \\\"fontFamily\\\": \\\"Inter, Helvetica, Arial, sans-serif\\\",\\n    \\\"title\\\": {\\n      \\\"fontSize\\\": 18,\\n      \\\"fontWeight\\\": \\\"bold\\\",\\n      \\\"color\\\": \\\"#1A1A1A\\\",\\n      \\\"lineHeight\\\": 1.3\\n    },\\n    \\\"subtitle\\\": {\\n      \\\"fontSize\\\": 13,\\n      \\\"fontWeight\\\": \\\"normal\\\",\\n      \\\"color\\\": \\\"#5D666F\\\",\\n      \\\"marginTop\\\": 4\\n    },\\n    \\\"source\\\": {\\n      \\\"fontSize\\\": 11,\\n      \\\"fontWeight\\\": \\\"normal\\\",\\n      \\\"color\\\": \\\"#999999\\\",\\n      \\\"position\\\": \\\"bottom-left\\\"\\n    },\\n    \\\"axisLabels\\\": {\\n      \\\"fontSize\\\": 12,\\n      \\\"color\\\": \\\"#5D666F\\\"\\n    }\\n  },\\n  \\\"style\\\": {\\n    \\\"lineInterpolation\\\": \\\"linear\\\",\\n    \\\"no3D\\\": true,\\n    \\\"noShadows\\\": true,\\n    \\\"noDecorations\\\": true\\n  }\\n}\\n\"}}],\"uuid\":\"d6a022b8-a9d1-49b6-8f28-a8504594c380\"}"
}
