{
  "run_id": "opus_none_task3_rep2",
  "model": "opus",
  "condition": "none",
  "task": "3",
  "task_complexity": "complex",
  "rep": 2,
  "timestamp": "2026-02-20T06:27:44+00:00",
  "duration_ms": 23645,
  "cli_tool": "claude",
  "raw_output": "{\"type\":\"result\",\"subtype\":\"success\",\"is_error\":false,\"duration_ms\":20995,\"duration_api_ms\":20744,\"num_turns\":2,\"result\":\"Here's the chart specification as JSON:\\n\\n```json\\n{\\n  \\\"chart_type\\\": \\\"line\\\",\\n  \\\"title\\\": {\\n    \\\"text\\\": \\\"Quarterly Revenue: AWS vs Azure vs GCP\\\",\\n    \\\"subtitle\\\": \\\"Azure overtook AWS as the top cloud provider by revenue in Q2 2024\\\"\\n  },\\n  \\\"source\\\": \\\"Company earnings reports, 2023–2024\\\",\\n  \\\"data\\\": [\\n    { \\\"quarter\\\": \\\"2023-Q1\\\", \\\"AWS\\\": 21.3, \\\"Azure\\\": 21.0, \\\"GCP\\\": 7.0 },\\n    { \\\"quarter\\\": \\\"2023-Q2\\\", \\\"AWS\\\": 22.1, \\\"Azure\\\": 23.0, \\\"GCP\\\": 8.0 },\\n    { \\\"quarter\\\": \\\"2023-Q3\\\", \\\"AWS\\\": 23.1, \\\"Azure\\\": 24.0, \\\"GCP\\\": 8.4 },\\n    { \\\"quarter\\\": \\\"2023-Q4\\\", \\\"AWS\\\": 24.2, \\\"Azure\\\": 25.0, \\\"GCP\\\": 9.2 },\\n    { \\\"quarter\\\": \\\"2024-Q1\\\", \\\"AWS\\\": 25.0, \\\"Azure\\\": 26.0, \\\"GCP\\\": 9.6 },\\n    { \\\"quarter\\\": \\\"2024-Q2\\\", \\\"AWS\\\": 26.0, \\\"Azure\\\": 28.0, \\\"GCP\\\": 10.3 },\\n    { \\\"quarter\\\": \\\"2024-Q3\\\", \\\"AWS\\\": 27.5, \\\"Azure\\\": 29.0, \\\"GCP\\\": 11.4 },\\n    { \\\"quarter\\\": \\\"2024-Q4\\\", \\\"AWS\\\": 28.8, \\\"Azure\\\": 30.0, \\\"GCP\\\": 12.0 }\\n  ],\\n  \\\"axes\\\": {\\n    \\\"x\\\": {\\n      \\\"field\\\": \\\"quarter\\\",\\n      \\\"label\\\": \\\"Quarter\\\"\\n    },\\n    \\\"y\\\": {\\n      \\\"label\\\": \\\"Revenue (USD Billions)\\\",\\n      \\\"min\\\": 0,\\n      \\\"max\\\": 35\\n    }\\n  },\\n  \\\"series\\\": [\\n    { \\\"field\\\": \\\"AWS\\\", \\\"color\\\": \\\"#FF9900\\\", \\\"strokeWidth\\\": 2.5 },\\n    { \\\"field\\\": \\\"Azure\\\", \\\"color\\\": \\\"#0078D4\\\", \\\"strokeWidth\\\": 2.5 },\\n    { \\\"field\\\": \\\"GCP\\\", \\\"color\\\": \\\"#4285F4\\\", \\\"strokeWidth\\\": 2.5 }\\n  ],\\n  \\\"annotations\\\": [\\n    {\\n      \\\"type\\\": \\\"point\\\",\\n      \\\"quarter\\\": \\\"2024-Q2\\\",\\n      \\\"label\\\": \\\"Azure overtakes AWS\\\",\\n      \\\"description\\\": \\\"Azure ($28.0B) surpasses AWS ($26.0B) by $2B\\\",\\n      \\\"style\\\": \\\"highlight_circle\\\"\\n    }\\n  ]\\n}\\n```\\n\\n**Notes on the spec:**\\n\\n- **Series colors** use each provider's brand color — AWS orange, Azure blue, GCP blue (lighter shade to distinguish from Azure)\\n- **Annotation** marks the Q2 2024 crossover point where Azure ($28.0B) pulled ahead of AWS ($26.0B)\\n- **Y-axis** starts at 0 with a max of 35 to give headroom above the highest value (Azure at $30B)\\n- One notable detail from the data: Azure actually first overtook AWS back in **Q2 2023** ($23.0B vs $22.1B), not Q2 2024 — the gap just widened significantly by Q2 2024\",\"stop_reason\":null,\"session_id\":\"65f0cccf-f9b1-4f56-afa6-6b5bd8ac08b7\",\"total_cost_usd\":0.0776655,\"usage\":{\"input_tokens\":4,\"cache_creation_input_tokens\":782,\"cache_read_input_tokens\":67416,\"output_tokens\":1562,\"server_tool_use\":{\"web_search_requests\":0,\"web_fetch_requests\":0},\"service_tier\":\"standard\",\"cache_creation\":{\"ephemeral_1h_input_tokens\":782,\"ephemeral_5m_input_tokens\":0},\"inference_geo\":\"\",\"iterations\":[],\"speed\":\"standard\"},\"modelUsage\":{\"claude-opus-4-6\":{\"inputTokens\":4,\"outputTokens\":1562,\"cacheReadInputTokens\":67416,\"cacheCreationInputTokens\":782,\"webSearchRequests\":0,\"costUSD\":0.0776655,\"contextWindow\":200000,\"maxOutputTokens\":32000}},\"permission_denials\":[{\"tool_name\":\"Write\",\"tool_use_id\":\"toolu_01Jjded6kjSoqiq4k8QMjttU\",\"tool_input\":{\"file_path\":\"/tmp/cloud_revenue_chart.json\",\"content\":\"{\\n  \\\"chart_type\\\": \\\"line\\\",\\n  \\\"title\\\": {\\n    \\\"text\\\": \\\"Quarterly Revenue: AWS vs Azure vs GCP\\\",\\n    \\\"subtitle\\\": \\\"Azure overtook AWS as the top cloud provider by revenue in Q2 2024\\\"\\n  },\\n  \\\"source\\\": \\\"Company earnings reports, 2023–2024\\\",\\n  \\\"data\\\": [\\n    { \\\"quarter\\\": \\\"2023-Q1\\\", \\\"AWS\\\": 21.3, \\\"Azure\\\": 21.0, \\\"GCP\\\": 7.0 },\\n    { \\\"quarter\\\": \\\"2023-Q2\\\", \\\"AWS\\\": 22.1, \\\"Azure\\\": 23.0, \\\"GCP\\\": 8.0 },\\n    { \\\"quarter\\\": \\\"2023-Q3\\\", \\\"AWS\\\": 23.1, \\\"Azure\\\": 24.0, \\\"GCP\\\": 8.4 },\\n    { \\\"quarter\\\": \\\"2023-Q4\\\", \\\"AWS\\\": 24.2, \\\"Azure\\\": 25.0, \\\"GCP\\\": 9.2 },\\n    { \\\"quarter\\\": \\\"2024-Q1\\\", \\\"AWS\\\": 25.0, \\\"Azure\\\": 26.0, \\\"GCP\\\": 9.6 },\\n    { \\\"quarter\\\": \\\"2024-Q2\\\", \\\"AWS\\\": 26.0, \\\"Azure\\\": 28.0, \\\"GCP\\\": 10.3 },\\n    { \\\"quarter\\\": \\\"2024-Q3\\\", \\\"AWS\\\": 27.5, \\\"Azure\\\": 29.0, \\\"GCP\\\": 11.4 },\\n    { \\\"quarter\\\": \\\"2024-Q4\\\", \\\"AWS\\\": 28.8, \\\"Azure\\\": 30.0, \\\"GCP\\\": 12.0 }\\n  ],\\n  \\\"axes\\\": {\\n    \\\"x\\\": {\\n      \\\"field\\\": \\\"quarter\\\",\\n      \\\"label\\\": \\\"Quarter\\\"\\n    },\\n    \\\"y\\\": {\\n      \\\"label\\\": \\\"Revenue (USD Billions)\\\",\\n      \\\"min\\\": 0,\\n      \\\"max\\\": 35\\n    }\\n  },\\n  \\\"series\\\": [\\n    { \\\"field\\\": \\\"AWS\\\", \\\"color\\\": \\\"#FF9900\\\", \\\"strokeWidth\\\": 2.5 },\\n    { \\\"field\\\": \\\"Azure\\\", \\\"color\\\": \\\"#0078D4\\\", \\\"strokeWidth\\\": 2.5 },\\n    { \\\"field\\\": \\\"GCP\\\", \\\"color\\\": \\\"#4285F4\\\", \\\"strokeWidth\\\": 2.5 }\\n  ],\\n  \\\"annotations\\\": [\\n    {\\n      \\\"type\\\": \\\"point\\\",\\n      \\\"quarter\\\": \\\"2024-Q2\\\",\\n      \\\"label\\\": \\\"Azure overtakes AWS\\\",\\n      \\\"description\\\": \\\"Azure ($28.0B) surpasses AWS ($26.0B) by $2B\\\",\\n      \\\"style\\\": \\\"highlight_circle\\\"\\n    }\\n  ]\\n}\\n\"}}],\"uuid\":\"a02bec40-2c62-4e30-9a20-27c416665e50\"}"
}
