{
  "run_id": "opus_none_task3_rep1",
  "model": "opus",
  "condition": "none",
  "task": "3",
  "task_complexity": "complex",
  "rep": 1,
  "timestamp": "2026-02-20T06:27:16+00:00",
  "duration_ms": 21432,
  "cli_tool": "claude",
  "raw_output": "{\"type\":\"result\",\"subtype\":\"success\",\"is_error\":false,\"duration_ms\":18481,\"duration_api_ms\":18198,\"num_turns\":2,\"result\":\"Here's the chart specification as JSON:\\n\\n```json\\n{\\n  \\\"chart_type\\\": \\\"line\\\",\\n  \\\"title\\\": {\\n    \\\"text\\\": \\\"Quarterly Revenue: AWS vs Azure vs GCP\\\",\\n    \\\"subtitle\\\": \\\"Azure overtook AWS as the top cloud provider by revenue in Q2 2024\\\"\\n  },\\n  \\\"source\\\": \\\"Company earnings reports, 2023–2024\\\",\\n  \\\"data\\\": [\\n    { \\\"quarter\\\": \\\"2023-Q1\\\", \\\"AWS\\\": 21.3, \\\"Azure\\\": 21.0, \\\"GCP\\\": 7.0 },\\n    { \\\"quarter\\\": \\\"2023-Q2\\\", \\\"AWS\\\": 22.1, \\\"Azure\\\": 23.0, \\\"GCP\\\": 8.0 },\\n    { \\\"quarter\\\": \\\"2023-Q3\\\", \\\"AWS\\\": 23.1, \\\"Azure\\\": 24.0, \\\"GCP\\\": 8.4 },\\n    { \\\"quarter\\\": \\\"2023-Q4\\\", \\\"AWS\\\": 24.2, \\\"Azure\\\": 25.0, \\\"GCP\\\": 9.2 },\\n    { \\\"quarter\\\": \\\"2024-Q1\\\", \\\"AWS\\\": 25.0, \\\"Azure\\\": 26.0, \\\"GCP\\\": 9.6 },\\n    { \\\"quarter\\\": \\\"2024-Q2\\\", \\\"AWS\\\": 26.0, \\\"Azure\\\": 28.0, \\\"GCP\\\": 10.3 },\\n    { \\\"quarter\\\": \\\"2024-Q3\\\", \\\"AWS\\\": 27.5, \\\"Azure\\\": 29.0, \\\"GCP\\\": 11.4 },\\n    { \\\"quarter\\\": \\\"2024-Q4\\\", \\\"AWS\\\": 28.8, \\\"Azure\\\": 30.0, \\\"GCP\\\": 12.0 }\\n  ],\\n  \\\"axes\\\": {\\n    \\\"x\\\": {\\n      \\\"field\\\": \\\"quarter\\\",\\n      \\\"label\\\": \\\"Quarter\\\"\\n    },\\n    \\\"y\\\": {\\n      \\\"field\\\": [\\\"AWS\\\", \\\"Azure\\\", \\\"GCP\\\"],\\n      \\\"label\\\": \\\"Revenue (USD Billions)\\\",\\n      \\\"min\\\": 0,\\n      \\\"max\\\": 35\\n    }\\n  },\\n  \\\"series\\\": [\\n    { \\\"name\\\": \\\"AWS\\\", \\\"field\\\": \\\"AWS\\\", \\\"color\\\": \\\"#FF9900\\\" },\\n    { \\\"name\\\": \\\"Azure\\\", \\\"field\\\": \\\"Azure\\\", \\\"color\\\": \\\"#0078D4\\\" },\\n    { \\\"name\\\": \\\"GCP\\\", \\\"field\\\": \\\"GCP\\\", \\\"color\\\": \\\"#4285F4\\\" }\\n  ],\\n  \\\"annotations\\\": [\\n    {\\n      \\\"type\\\": \\\"point\\\",\\n      \\\"quarter\\\": \\\"2024-Q2\\\",\\n      \\\"label\\\": \\\"Azure overtakes AWS\\\",\\n      \\\"description\\\": \\\"Azure ($28.0B) surpasses AWS ($26.0B) by $2B\\\",\\n      \\\"style\\\": \\\"highlight_marker\\\"\\n    }\\n  ]\\n}\\n```\\n\\nKey details:\\n\\n- **chart_type**: Line chart to show revenue trends over time\\n- **Series colors**: Brand colors for each provider (AWS orange, Azure blue, GCP blue)\\n- **Annotation**: Highlights the Q2 2024 crossover point where Azure ($28.0B) surpassed AWS ($26.0B)\\n- **Y-axis**: Starts at 0 with max of 35 to give room above the highest value (Azure at $30B)\\n- **Source**: Attributed at the top level\",\"stop_reason\":null,\"session_id\":\"fffa9b8b-5110-4906-a08e-053254ca6221\",\"total_cost_usd\":0.09391050000000001,\"usage\":{\"input_tokens\":4,\"cache_creation_input_tokens\":3724,\"cache_read_input_tokens\":64481,\"output_tokens\":1535,\"server_tool_use\":{\"web_search_requests\":0,\"web_fetch_requests\":0},\"service_tier\":\"standard\",\"cache_creation\":{\"ephemeral_1h_input_tokens\":3724,\"ephemeral_5m_input_tokens\":0},\"inference_geo\":\"\",\"iterations\":[],\"speed\":\"standard\"},\"modelUsage\":{\"claude-opus-4-6\":{\"inputTokens\":4,\"outputTokens\":1535,\"cacheReadInputTokens\":64481,\"cacheCreationInputTokens\":3724,\"webSearchRequests\":0,\"costUSD\":0.09391050000000001,\"contextWindow\":200000,\"maxOutputTokens\":32000}},\"permission_denials\":[{\"tool_name\":\"Write\",\"tool_use_id\":\"toolu_015So4eHY47czDJDxvKfJv3Q\",\"tool_input\":{\"file_path\":\"/tmp/cloud_revenue_chart.json\",\"content\":\"{\\n  \\\"chart_type\\\": \\\"line\\\",\\n  \\\"title\\\": {\\n    \\\"text\\\": \\\"Quarterly Revenue: AWS vs Azure vs GCP\\\",\\n    \\\"subtitle\\\": \\\"Azure overtook AWS as the top cloud provider by revenue in Q2 2024\\\"\\n  },\\n  \\\"source\\\": \\\"Company earnings reports, 2023–2024\\\",\\n  \\\"data\\\": [\\n    { \\\"quarter\\\": \\\"2023-Q1\\\", \\\"AWS\\\": 21.3, \\\"Azure\\\": 21.0, \\\"GCP\\\": 7.0 },\\n    { \\\"quarter\\\": \\\"2023-Q2\\\", \\\"AWS\\\": 22.1, \\\"Azure\\\": 23.0, \\\"GCP\\\": 8.0 },\\n    { \\\"quarter\\\": \\\"2023-Q3\\\", \\\"AWS\\\": 23.1, \\\"Azure\\\": 24.0, \\\"GCP\\\": 8.4 },\\n    { \\\"quarter\\\": \\\"2023-Q4\\\", \\\"AWS\\\": 24.2, \\\"Azure\\\": 25.0, \\\"GCP\\\": 9.2 },\\n    { \\\"quarter\\\": \\\"2024-Q1\\\", \\\"AWS\\\": 25.0, \\\"Azure\\\": 26.0, \\\"GCP\\\": 9.6 },\\n    { \\\"quarter\\\": \\\"2024-Q2\\\", \\\"AWS\\\": 26.0, \\\"Azure\\\": 28.0, \\\"GCP\\\": 10.3 },\\n    { \\\"quarter\\\": \\\"2024-Q3\\\", \\\"AWS\\\": 27.5, \\\"Azure\\\": 29.0, \\\"GCP\\\": 11.4 },\\n    { \\\"quarter\\\": \\\"2024-Q4\\\", \\\"AWS\\\": 28.8, \\\"Azure\\\": 30.0, \\\"GCP\\\": 12.0 }\\n  ],\\n  \\\"axes\\\": {\\n    \\\"x\\\": {\\n      \\\"field\\\": \\\"quarter\\\",\\n      \\\"label\\\": \\\"Quarter\\\"\\n    },\\n    \\\"y\\\": {\\n      \\\"field\\\": [\\\"AWS\\\", \\\"Azure\\\", \\\"GCP\\\"],\\n      \\\"label\\\": \\\"Revenue (USD Billions)\\\",\\n      \\\"min\\\": 0,\\n      \\\"max\\\": 35\\n    }\\n  },\\n  \\\"series\\\": [\\n    { \\\"name\\\": \\\"AWS\\\", \\\"field\\\": \\\"AWS\\\", \\\"color\\\": \\\"#FF9900\\\" },\\n    { \\\"name\\\": \\\"Azure\\\", \\\"field\\\": \\\"Azure\\\", \\\"color\\\": \\\"#0078D4\\\" },\\n    { \\\"name\\\": \\\"GCP\\\", \\\"field\\\": \\\"GCP\\\", \\\"color\\\": \\\"#4285F4\\\" }\\n  ],\\n  \\\"annotations\\\": [\\n    {\\n      \\\"type\\\": \\\"point\\\",\\n      \\\"quarter\\\": \\\"2024-Q2\\\",\\n      \\\"label\\\": \\\"Azure overtakes AWS\\\",\\n      \\\"description\\\": \\\"Azure ($28.0B) surpasses AWS ($26.0B) by $2B\\\",\\n      \\\"style\\\": \\\"highlight_marker\\\"\\n    }\\n  ]\\n}\\n\"}}],\"uuid\":\"52bafd38-38c6-46b4-854f-38a991a76a4e\"}"
}
