{
  "run_id": "opus_none_task3_rep3",
  "model": "opus",
  "condition": "none",
  "task": "3",
  "task_complexity": "complex",
  "rep": 3,
  "timestamp": "2026-02-20T06:28:12+00:00",
  "duration_ms": 22346,
  "cli_tool": "claude",
  "raw_output": "{\"type\":\"result\",\"subtype\":\"success\",\"is_error\":false,\"duration_ms\":19554,\"duration_api_ms\":19354,\"num_turns\":2,\"result\":\"Here's the chart specification as JSON:\\n\\n```json\\n{\\n  \\\"chart_type\\\": \\\"line\\\",\\n  \\\"title\\\": {\\n    \\\"text\\\": \\\"Quarterly Revenue: AWS vs Azure vs GCP\\\",\\n    \\\"subtitle\\\": \\\"Azure overtook AWS as the top cloud provider by revenue in Q2 2024\\\"\\n  },\\n  \\\"source\\\": \\\"Company earnings reports, 2023–2024\\\",\\n  \\\"data\\\": [\\n    { \\\"quarter\\\": \\\"2023-Q1\\\", \\\"AWS\\\": 21.3, \\\"Azure\\\": 21.0, \\\"GCP\\\": 7.0 },\\n    { \\\"quarter\\\": \\\"2023-Q2\\\", \\\"AWS\\\": 22.1, \\\"Azure\\\": 23.0, \\\"GCP\\\": 8.0 },\\n    { \\\"quarter\\\": \\\"2023-Q3\\\", \\\"AWS\\\": 23.1, \\\"Azure\\\": 24.0, \\\"GCP\\\": 8.4 },\\n    { \\\"quarter\\\": \\\"2023-Q4\\\", \\\"AWS\\\": 24.2, \\\"Azure\\\": 25.0, \\\"GCP\\\": 9.2 },\\n    { \\\"quarter\\\": \\\"2024-Q1\\\", \\\"AWS\\\": 25.0, \\\"Azure\\\": 26.0, \\\"GCP\\\": 9.6 },\\n    { \\\"quarter\\\": \\\"2024-Q2\\\", \\\"AWS\\\": 26.0, \\\"Azure\\\": 28.0, \\\"GCP\\\": 10.3 },\\n    { \\\"quarter\\\": \\\"2024-Q3\\\", \\\"AWS\\\": 27.5, \\\"Azure\\\": 29.0, \\\"GCP\\\": 11.4 },\\n    { \\\"quarter\\\": \\\"2024-Q4\\\", \\\"AWS\\\": 28.8, \\\"Azure\\\": 30.0, \\\"GCP\\\": 12.0 }\\n  ],\\n  \\\"axes\\\": {\\n    \\\"x\\\": {\\n      \\\"field\\\": \\\"quarter\\\",\\n      \\\"label\\\": \\\"Quarter\\\"\\n    },\\n    \\\"y\\\": {\\n      \\\"field\\\": [\\\"AWS\\\", \\\"Azure\\\", \\\"GCP\\\"],\\n      \\\"label\\\": \\\"Revenue (USD Billions)\\\",\\n      \\\"min\\\": 0,\\n      \\\"max\\\": 35\\n    }\\n  },\\n  \\\"series\\\": [\\n    { \\\"name\\\": \\\"AWS\\\", \\\"field\\\": \\\"AWS\\\", \\\"color\\\": \\\"#FF9900\\\" },\\n    { \\\"name\\\": \\\"Azure\\\", \\\"field\\\": \\\"Azure\\\", \\\"color\\\": \\\"#0078D4\\\" },\\n    { \\\"name\\\": \\\"GCP\\\", \\\"field\\\": \\\"GCP\\\", \\\"color\\\": \\\"#4285F4\\\" }\\n  ],\\n  \\\"annotations\\\": [\\n    {\\n      \\\"type\\\": \\\"point\\\",\\n      \\\"quarter\\\": \\\"2024-Q2\\\",\\n      \\\"label\\\": \\\"Azure overtakes AWS\\\",\\n      \\\"description\\\": \\\"Azure reached $28B vs AWS $26B, marking the first quarter Azure led in cloud revenue\\\",\\n      \\\"style\\\": \\\"highlight_circle\\\"\\n    }\\n  ]\\n}\\n```\\n\\nKey details in the spec:\\n\\n- **chart_type**: Line chart to show trends over time\\n- **Series colors**: Brand colors for each provider — AWS orange (#FF9900), Azure blue (#0078D4), GCP blue (#4285F4)\\n- **Y-axis**: Starts at 0 with a max of 35 to give headroom above the highest value (Azure $30B)\\n- **Annotation**: Highlights the Q2 2024 crossover point where Azure ($28B) overtook AWS ($26B)\\n- **Source**: Attributed at the spec level for rendering as a footnote\",\"stop_reason\":null,\"session_id\":\"b4c7a808-b7b1-47a4-bf74-b250293d1024\",\"total_cost_usd\":0.077428,\"usage\":{\"input_tokens\":4,\"cache_creation_input_tokens\":788,\"cache_read_input_tokens\":67416,\"output_tokens\":1551,\"server_tool_use\":{\"web_search_requests\":0,\"web_fetch_requests\":0},\"service_tier\":\"standard\",\"cache_creation\":{\"ephemeral_1h_input_tokens\":788,\"ephemeral_5m_input_tokens\":0},\"inference_geo\":\"\",\"iterations\":[],\"speed\":\"standard\"},\"modelUsage\":{\"claude-opus-4-6\":{\"inputTokens\":4,\"outputTokens\":1551,\"cacheReadInputTokens\":67416,\"cacheCreationInputTokens\":788,\"webSearchRequests\":0,\"costUSD\":0.077428,\"contextWindow\":200000,\"maxOutputTokens\":32000}},\"permission_denials\":[{\"tool_name\":\"Write\",\"tool_use_id\":\"toolu_01WfStr7LqEST1MMF4ANwiKT\",\"tool_input\":{\"file_path\":\"/tmp/cloud_revenue_chart.json\",\"content\":\"{\\n  \\\"chart_type\\\": \\\"line\\\",\\n  \\\"title\\\": {\\n    \\\"text\\\": \\\"Quarterly Revenue: AWS vs Azure vs GCP\\\",\\n    \\\"subtitle\\\": \\\"Azure overtook AWS as the top cloud provider by revenue in Q2 2024\\\"\\n  },\\n  \\\"source\\\": \\\"Company earnings reports, 2023–2024\\\",\\n  \\\"data\\\": [\\n    { \\\"quarter\\\": \\\"2023-Q1\\\", \\\"AWS\\\": 21.3, \\\"Azure\\\": 21.0, \\\"GCP\\\": 7.0 },\\n    { \\\"quarter\\\": \\\"2023-Q2\\\", \\\"AWS\\\": 22.1, \\\"Azure\\\": 23.0, \\\"GCP\\\": 8.0 },\\n    { \\\"quarter\\\": \\\"2023-Q3\\\", \\\"AWS\\\": 23.1, \\\"Azure\\\": 24.0, \\\"GCP\\\": 8.4 },\\n    { \\\"quarter\\\": \\\"2023-Q4\\\", \\\"AWS\\\": 24.2, \\\"Azure\\\": 25.0, \\\"GCP\\\": 9.2 },\\n    { \\\"quarter\\\": \\\"2024-Q1\\\", \\\"AWS\\\": 25.0, \\\"Azure\\\": 26.0, \\\"GCP\\\": 9.6 },\\n    { \\\"quarter\\\": \\\"2024-Q2\\\", \\\"AWS\\\": 26.0, \\\"Azure\\\": 28.0, \\\"GCP\\\": 10.3 },\\n    { \\\"quarter\\\": \\\"2024-Q3\\\", \\\"AWS\\\": 27.5, \\\"Azure\\\": 29.0, \\\"GCP\\\": 11.4 },\\n    { \\\"quarter\\\": \\\"2024-Q4\\\", \\\"AWS\\\": 28.8, \\\"Azure\\\": 30.0, \\\"GCP\\\": 12.0 }\\n  ],\\n  \\\"axes\\\": {\\n    \\\"x\\\": {\\n      \\\"field\\\": \\\"quarter\\\",\\n      \\\"label\\\": \\\"Quarter\\\"\\n    },\\n    \\\"y\\\": {\\n      \\\"field\\\": [\\\"AWS\\\", \\\"Azure\\\", \\\"GCP\\\"],\\n      \\\"label\\\": \\\"Revenue (USD Billions)\\\",\\n      \\\"min\\\": 0,\\n      \\\"max\\\": 35\\n    }\\n  },\\n  \\\"series\\\": [\\n    { \\\"name\\\": \\\"AWS\\\", \\\"field\\\": \\\"AWS\\\", \\\"color\\\": \\\"#FF9900\\\" },\\n    { \\\"name\\\": \\\"Azure\\\", \\\"field\\\": \\\"Azure\\\", \\\"color\\\": \\\"#0078D4\\\" },\\n    { \\\"name\\\": \\\"GCP\\\", \\\"field\\\": \\\"GCP\\\", \\\"color\\\": \\\"#4285F4\\\" }\\n  ],\\n  \\\"annotations\\\": [\\n    {\\n      \\\"type\\\": \\\"point\\\",\\n      \\\"quarter\\\": \\\"2024-Q2\\\",\\n      \\\"label\\\": \\\"Azure overtakes AWS\\\",\\n      \\\"description\\\": \\\"Azure reached $28B vs AWS $26B, marking the first quarter Azure led in cloud revenue\\\",\\n      \\\"style\\\": \\\"highlight_circle\\\"\\n    }\\n  ]\\n}\\n\"}}],\"uuid\":\"b1078187-d2a6-447b-b6ee-e6908c3f2911\"}"
}
