{
  "run_id": "opus_markdown_task3_rep2",
  "model": "opus",
  "condition": "markdown",
  "task": "3",
  "task_complexity": "complex",
  "rep": 2,
  "timestamp": "2026-02-20T06:35:04+00:00",
  "duration_ms": 91236,
  "cli_tool": "claude",
  "raw_output": "{\"type\":\"result\",\"subtype\":\"success\",\"is_error\":false,\"duration_ms\":54008,\"duration_api_ms\":53958,\"num_turns\":2,\"result\":\"Here's the chart specification:\\n\\n```json\\n{\\n  \\\"chart\\\": {\\n    \\\"type\\\": \\\"line\\\",\\n    \\\"title\\\": \\\"Azure overtook AWS as the largest cloud provider in 2023\\\",\\n    \\\"subtitle\\\": \\\"Quarterly cloud revenue, USD billions\\\",\\n    \\\"source\\\": \\\"Source: Company earnings reports, 2023–2024\\\",\\n    \\\"aspectRatio\\\": \\\"16:9\\\",\\n    \\\"width\\\": 800,\\n    \\\"height\\\": 450,\\n    \\\"background\\\": \\\"#F5F5F5\\\",\\n    \\\"margins\\\": { \\\"top\\\": 80, \\\"right\\\": 100, \\\"bottom\\\": 60, \\\"left\\\": 60 }\\n  },\\n  \\\"axes\\\": {\\n    \\\"x\\\": {\\n      \\\"field\\\": \\\"quarter\\\",\\n      \\\"gridlines\\\": false,\\n      \\\"spine\\\": true,\\n      \\\"spineColor\\\": \\\"#333333\\\"\\n    },\\n    \\\"y\\\": {\\n      \\\"field\\\": \\\"revenue\\\",\\n      \\\"min\\\": 0,\\n      \\\"max\\\": 35,\\n      \\\"tickValues\\\": [0, 5, 10, 15, 20, 25, 30, 35],\\n      \\\"tickFormat\\\": \\\"${}B\\\",\\n      \\\"gridlines\\\": true,\\n      \\\"gridlineStyle\\\": {\\n        \\\"color\\\": \\\"#D0D0D0\\\",\\n        \\\"strokeDasharray\\\": \\\"4 2\\\",\\n        \\\"strokeWidth\\\": 0.5\\n      },\\n      \\\"spine\\\": false\\n    },\\n    \\\"removeTopSpine\\\": true,\\n    \\\"removeRightSpine\\\": true\\n  },\\n  \\\"data\\\": [\\n    { \\\"quarter\\\": \\\"Q1 '23\\\", \\\"AWS\\\": 21.3, \\\"Azure\\\": 21.0, \\\"GCP\\\": 7.0 },\\n    { \\\"quarter\\\": \\\"Q2 '23\\\", \\\"AWS\\\": 22.1, \\\"Azure\\\": 23.0, \\\"GCP\\\": 8.0 },\\n    { \\\"quarter\\\": \\\"Q3 '23\\\", \\\"AWS\\\": 23.1, \\\"Azure\\\": 24.0, \\\"GCP\\\": 8.4 },\\n    { \\\"quarter\\\": \\\"Q4 '23\\\", \\\"AWS\\\": 24.2, \\\"Azure\\\": 25.0, \\\"GCP\\\": 9.2 },\\n    { \\\"quarter\\\": \\\"Q1 '24\\\", \\\"AWS\\\": 25.0, \\\"Azure\\\": 26.0, \\\"GCP\\\": 9.6 },\\n    { \\\"quarter\\\": \\\"Q2 '24\\\", \\\"AWS\\\": 26.0, \\\"Azure\\\": 28.0, \\\"GCP\\\": 10.3 },\\n    { \\\"quarter\\\": \\\"Q3 '24\\\", \\\"AWS\\\": 27.5, \\\"Azure\\\": 29.0, \\\"GCP\\\": 11.4 },\\n    { \\\"quarter\\\": \\\"Q4 '24\\\", \\\"AWS\\\": 28.8, \\\"Azure\\\": 30.0, \\\"GCP\\\": 12.0 }\\n  },\\n  \\\"series\\\": [\\n    {\\n      \\\"name\\\": \\\"Azure\\\",\\n      \\\"field\\\": \\\"Azure\\\",\\n      \\\"color\\\": \\\"#C74634\\\",\\n      \\\"strokeWidth\\\": 3,\\n      \\\"directLabel\\\": {\\n        \\\"text\\\": \\\"Azure\\\",\\n        \\\"position\\\": \\\"right\\\",\\n        \\\"offsetX\\\": 8,\\n        \\\"fontWeight\\\": \\\"bold\\\",\\n        \\\"fontSize\\\": 13,\\n        \\\"color\\\": \\\"#C74634\\\"\\n      }\\n    },\\n    {\\n      \\\"name\\\": \\\"AWS\\\",\\n      \\\"field\\\": \\\"AWS\\\",\\n      \\\"color\\\": \\\"#1A476F\\\",\\n      \\\"strokeWidth\\\": 3,\\n      \\\"directLabel\\\": {\\n        \\\"text\\\": \\\"AWS\\\",\\n        \\\"position\\\": \\\"right\\\",\\n        \\\"offsetX\\\": 8,\\n        \\\"fontWeight\\\": \\\"bold\\\",\\n        \\\"fontSize\\\": 13,\\n        \\\"color\\\": \\\"#1A476F\\\"\\n      }\\n    },\\n    {\\n      \\\"name\\\": \\\"GCP\\\",\\n      \\\"field\\\": \\\"GCP\\\",\\n      \\\"color\\\": \\\"#5D666F\\\",\\n      \\\"strokeWidth\\\": 2,\\n      \\\"directLabel\\\": {\\n        \\\"text\\\": \\\"GCP\\\",\\n        \\\"position\\\": \\\"right\\\",\\n        \\\"offsetX\\\": 8,\\n        \\\"fontWeight\\\": \\\"normal\\\",\\n        \\\"fontSize\\\": 13,\\n        \\\"color\\\": \\\"#5D666F\\\"\\n      }\\n    }\\n  ],\\n  \\\"annotations\\\": [\\n    {\\n      \\\"type\\\": \\\"point\\\",\\n      \\\"dataIndex\\\": 1,\\n      \\\"series\\\": \\\"Azure\\\",\\n      \\\"marker\\\": {\\n        \\\"shape\\\": \\\"circle\\\",\\n        \\\"radius\\\": 5,\\n        \\\"fill\\\": \\\"#C74634\\\",\\n        \\\"stroke\\\": \\\"#FFFFFF\\\",\\n        \\\"strokeWidth\\\": 2\\n      },\\n      \\\"label\\\": {\\n        \\\"text\\\": \\\"Azure first overtakes AWS\\\\nin Q2 2023 ($23B vs $22.1B)\\\",\\n        \\\"fontSize\\\": 11,\\n        \\\"color\\\": \\\"#333333\\\",\\n        \\\"offsetX\\\": -20,\\n        \\\"offsetY\\\": -30,\\n        \\\"maxWidth\\\": 160\\n      },\\n      \\\"connector\\\": {\\n        \\\"type\\\": \\\"line\\\",\\n        \\\"stroke\\\": \\\"#999999\\\",\\n        \\\"strokeWidth\\\": 1\\n      }\\n    },\\n    {\\n      \\\"type\\\": \\\"point\\\",\\n      \\\"dataIndex\\\": 1,\\n      \\\"series\\\": \\\"AWS\\\",\\n      \\\"marker\\\": {\\n        \\\"shape\\\": \\\"circle\\\",\\n        \\\"radius\\\": 5,\\n        \\\"fill\\\": \\\"#1A476F\\\",\\n        \\\"stroke\\\": \\\"#FFFFFF\\\",\\n        \\\"strokeWidth\\\": 2\\n      }\\n    }\\n  ],\\n  \\\"typography\\\": {\\n    \\\"fontFamily\\\": \\\"Inter, Helvetica Neue, Helvetica, Arial, sans-serif\\\",\\n    \\\"title\\\": { \\\"fontSize\\\": 20, \\\"fontWeight\\\": \\\"bold\\\", \\\"color\\\": \\\"#1A1A1A\\\" },\\n    \\\"subtitle\\\": { \\\"fontSize\\\": 14, \\\"fontWeight\\\": \\\"normal\\\", \\\"color\\\": \\\"#5D666F\\\", \\\"marginTop\\\": 6 },\\n    \\\"source\\\": { \\\"fontSize\\\": 11, \\\"color\\\": \\\"#999999\\\", \\\"position\\\": \\\"bottom-left\\\" },\\n    \\\"axisLabels\\\": { \\\"fontSize\\\": 12, \\\"color\\\": \\\"#5D666F\\\" }\\n  },\\n  \\\"style\\\": {\\n    \\\"lineJoin\\\": \\\"round\\\",\\n    \\\"pointsOnLine\\\": false,\\n    \\\"no3D\\\": true,\\n    \\\"noDropShadows\\\": true,\\n    \\\"noDecorations\\\": true\\n  }\\n}\\n```\\n\\nKey design decisions following the style guidelines:\\n\\n- **Title as insight**: \\\"Azure overtook AWS as the largest cloud provider in 2023\\\" tells the story, not just \\\"Cloud Revenue by Provider\\\"\\n- **Accent color for the star**: Azure gets `#C74634` (red accent) since it's the highlight of the story; AWS gets `#1A476F` (primary blue); GCP gets `#5D666F` (gray, supporting role)\\n- **Direct labels** instead of a legend, since there are only 3 series\\n- **Annotation at the crossover** (Q2 '23) with circle markers on both lines and a callout noting the exact figures\\n- **Y-axis starts at zero** and uses dashed gridlines\\n- **Top and right spines removed**\\n- **16:9 aspect ratio** for time series\\n- **No chartjunk**: no 3D, shadows, or decorations\\n\\nNote: Looking at the data more carefully, Azure actually first overtakes AWS in **Q2 2023** ($23.0B vs $22.1B), not Q2 2024 as stated in the prompt. The annotation reflects what the data shows. If the intended insight is different, the crossover quarter in the annotation can be adjusted.\",\"stop_reason\":null,\"session_id\":\"b2d80c0a-9309-467e-8852-65862f2cd2e7\",\"total_cost_usd\":0.13004575000000002,\"usage\":{\"input_tokens\":4,\"cache_creation_input_tokens\":1755,\"cache_read_input_tokens\":62714,\"output_tokens\":3508,\"server_tool_use\":{\"web_search_requests\":0,\"web_fetch_requests\":0},\"service_tier\":\"standard\",\"cache_creation\":{\"ephemeral_1h_input_tokens\":1755,\"ephemeral_5m_input_tokens\":0},\"inference_geo\":\"\",\"iterations\":[],\"speed\":\"standard\"},\"modelUsage\":{\"claude-opus-4-6\":{\"inputTokens\":4,\"outputTokens\":3508,\"cacheReadInputTokens\":62714,\"cacheCreationInputTokens\":1755,\"webSearchRequests\":0,\"costUSD\":0.13004575000000002,\"contextWindow\":200000,\"maxOutputTokens\":32000}},\"permission_denials\":[{\"tool_name\":\"Write\",\"tool_use_id\":\"toolu_01TGVDRAjBriJZe25eEc4Zjy\",\"tool_input\":{\"file_path\":\"/tmp/cloud_revenue_chart.json\",\"content\":\"{\\n  \\\"chart\\\": {\\n    \\\"type\\\": \\\"line\\\",\\n    \\\"title\\\": \\\"Azure overtook AWS as the largest cloud provider in 2023\\\",\\n    \\\"subtitle\\\": \\\"Quarterly cloud revenue, USD billions\\\",\\n    \\\"source\\\": \\\"Source: Company earnings reports, 2023–2024\\\",\\n    \\\"aspectRatio\\\": \\\"16:9\\\",\\n    \\\"width\\\": 800,\\n    \\\"height\\\": 450,\\n    \\\"background\\\": \\\"#F5F5F5\\\",\\n    \\\"margins\\\": {\\n      \\\"top\\\": 80,\\n      \\\"right\\\": 100,\\n      \\\"bottom\\\": 60,\\n      \\\"left\\\": 60\\n    }\\n  },\\n  \\\"axes\\\": {\\n    \\\"x\\\": {\\n      \\\"field\\\": \\\"quarter\\\",\\n      \\\"label\\\": null,\\n      \\\"tickFormat\\\": null,\\n      \\\"gridlines\\\": false,\\n      \\\"spine\\\": true,\\n      \\\"spineColor\\\": \\\"#333333\\\"\\n    },\\n    \\\"y\\\": {\\n      \\\"field\\\": \\\"revenue\\\",\\n      \\\"label\\\": null,\\n      \\\"min\\\": 0,\\n      \\\"max\\\": 35,\\n      \\\"tickValues\\\": [0, 5, 10, 15, 20, 25, 30, 35],\\n      \\\"tickFormat\\\": \\\"${}B\\\",\\n      \\\"gridlines\\\": true,\\n      \\\"gridlineStyle\\\": {\\n        \\\"color\\\": \\\"#D0D0D0\\\",\\n        \\\"strokeDasharray\\\": \\\"4 2\\\",\\n        \\\"strokeWidth\\\": 0.5\\n      },\\n      \\\"spine\\\": false\\n    },\\n    \\\"removeTopSpine\\\": true,\\n    \\\"removeRightSpine\\\": true\\n  },\\n  \\\"data\\\": [\\n    { \\\"quarter\\\": \\\"Q1 '23\\\", \\\"AWS\\\": 21.3, \\\"Azure\\\": 21.0, \\\"GCP\\\": 7.0 },\\n    { \\\"quarter\\\": \\\"Q2 '23\\\", \\\"AWS\\\": 22.1, \\\"Azure\\\": 23.0, \\\"GCP\\\": 8.0 },\\n    { \\\"quarter\\\": \\\"Q3 '23\\\", \\\"AWS\\\": 23.1, \\\"Azure\\\": 24.0, \\\"GCP\\\": 8.4 },\\n    { \\\"quarter\\\": \\\"Q4 '23\\\", \\\"AWS\\\": 24.2, \\\"Azure\\\": 25.0, \\\"GCP\\\": 9.2 },\\n    { \\\"quarter\\\": \\\"Q1 '24\\\", \\\"AWS\\\": 25.0, \\\"Azure\\\": 26.0, \\\"GCP\\\": 9.6 },\\n    { \\\"quarter\\\": \\\"Q2 '24\\\", \\\"AWS\\\": 26.0, \\\"Azure\\\": 28.0, \\\"GCP\\\": 10.3 },\\n    { \\\"quarter\\\": \\\"Q3 '24\\\", \\\"AWS\\\": 27.5, \\\"Azure\\\": 29.0, \\\"GCP\\\": 11.4 },\\n    { \\\"quarter\\\": \\\"Q4 '24\\\", \\\"AWS\\\": 28.8, \\\"Azure\\\": 30.0, \\\"GCP\\\": 12.0 }\\n  ],\\n  \\\"series\\\": [\\n    {\\n      \\\"name\\\": \\\"Azure\\\",\\n      \\\"field\\\": \\\"Azure\\\",\\n      \\\"color\\\": \\\"#C74634\\\",\\n      \\\"strokeWidth\\\": 3,\\n      \\\"directLabel\\\": {\\n        \\\"text\\\": \\\"Azure\\\",\\n        \\\"position\\\": \\\"right\\\",\\n        \\\"offsetX\\\": 8,\\n        \\\"offsetY\\\": 0,\\n        \\\"fontWeight\\\": \\\"bold\\\",\\n        \\\"fontSize\\\": 13,\\n        \\\"color\\\": \\\"#C74634\\\"\\n      }\\n    },\\n    {\\n      \\\"name\\\": \\\"AWS\\\",\\n      \\\"field\\\": \\\"AWS\\\",\\n      \\\"color\\\": \\\"#1A476F\\\",\\n      \\\"strokeWidth\\\": 3,\\n      \\\"directLabel\\\": {\\n        \\\"text\\\": \\\"AWS\\\",\\n        \\\"position\\\": \\\"right\\\",\\n        \\\"offsetX\\\": 8,\\n        \\\"offsetY\\\": 0,\\n        \\\"fontWeight\\\": \\\"bold\\\",\\n        \\\"fontSize\\\": 13,\\n        \\\"color\\\": \\\"#1A476F\\\"\\n      }\\n    },\\n    {\\n      \\\"name\\\": \\\"GCP\\\",\\n      \\\"field\\\": \\\"GCP\\\",\\n      \\\"color\\\": \\\"#5D666F\\\",\\n      \\\"strokeWidth\\\": 2,\\n      \\\"directLabel\\\": {\\n        \\\"text\\\": \\\"GCP\\\",\\n        \\\"position\\\": \\\"right\\\",\\n        \\\"offsetX\\\": 8,\\n        \\\"offsetY\\\": 0,\\n        \\\"fontWeight\\\": \\\"normal\\\",\\n        \\\"fontSize\\\": 13,\\n        \\\"color\\\": \\\"#5D666F\\\"\\n      }\\n    }\\n  ],\\n  \\\"annotations\\\": [\\n    {\\n      \\\"type\\\": \\\"point\\\",\\n      \\\"dataIndex\\\": 1,\\n      \\\"series\\\": \\\"Azure\\\",\\n      \\\"marker\\\": {\\n        \\\"shape\\\": \\\"circle\\\",\\n        \\\"radius\\\": 5,\\n        \\\"fill\\\": \\\"#C74634\\\",\\n        \\\"stroke\\\": \\\"#FFFFFF\\\",\\n        \\\"strokeWidth\\\": 2\\n      },\\n      \\\"label\\\": {\\n        \\\"text\\\": \\\"Azure first overtakes AWS\\\\nin Q2 2023 ($23B vs $22.1B)\\\",\\n        \\\"fontSize\\\": 11,\\n        \\\"color\\\": \\\"#333333\\\",\\n        \\\"offsetX\\\": -20,\\n        \\\"offsetY\\\": -30,\\n        \\\"maxWidth\\\": 160,\\n        \\\"lineHeight\\\": 1.3\\n      },\\n      \\\"connector\\\": {\\n        \\\"type\\\": \\\"line\\\",\\n        \\\"stroke\\\": \\\"#999999\\\",\\n        \\\"strokeWidth\\\": 1\\n      }\\n    },\\n    {\\n      \\\"type\\\": \\\"point\\\",\\n      \\\"dataIndex\\\": 1,\\n      \\\"series\\\": \\\"AWS\\\",\\n      \\\"marker\\\": {\\n        \\\"shape\\\": \\\"circle\\\",\\n        \\\"radius\\\": 5,\\n        \\\"fill\\\": \\\"#1A476F\\\",\\n        \\\"stroke\\\": \\\"#FFFFFF\\\",\\n        \\\"strokeWidth\\\": 2\\n      }\\n    }\\n  ],\\n  \\\"typography\\\": {\\n    \\\"fontFamily\\\": \\\"Inter, Helvetica Neue, Helvetica, Arial, sans-serif\\\",\\n    \\\"title\\\": {\\n      \\\"fontSize\\\": 20,\\n      \\\"fontWeight\\\": \\\"bold\\\",\\n      \\\"color\\\": \\\"#1A1A1A\\\",\\n      \\\"lineHeight\\\": 1.2\\n    },\\n    \\\"subtitle\\\": {\\n      \\\"fontSize\\\": 14,\\n      \\\"fontWeight\\\": \\\"normal\\\",\\n      \\\"color\\\": \\\"#5D666F\\\",\\n      \\\"marginTop\\\": 6\\n    },\\n    \\\"source\\\": {\\n      \\\"fontSize\\\": 11,\\n      \\\"fontWeight\\\": \\\"normal\\\",\\n      \\\"color\\\": \\\"#999999\\\",\\n      \\\"position\\\": \\\"bottom-left\\\"\\n    },\\n    \\\"axisLabels\\\": {\\n      \\\"fontSize\\\": 12,\\n      \\\"color\\\": \\\"#5D666F\\\"\\n    }\\n  },\\n  \\\"style\\\": {\\n    \\\"lineJoin\\\": \\\"round\\\",\\n    \\\"pointsOnLine\\\": false,\\n    \\\"no3D\\\": true,\\n    \\\"noDropShadows\\\": true,\\n    \\\"noDecorations\\\": true\\n  }\\n}\\n\"}}],\"uuid\":\"d059226e-2635-4ffe-99ea-c58b435b9fd9\"}"
}
